antelope_background/__init__.py
antelope_background/lci_tester.py
antelope_background/background/__init__.py
antelope_background/background/flat_background.py
antelope_background/background/foreground.py
antelope_background/background/implementation.py
antelope_background/background/tests/__init__.py
antelope_background/background/tests/test_flat_background.py
antelope_background/background/tests/test_implementation.py
antelope_background/engine/__init__.py
antelope_background/engine/background_engine.py
antelope_background/engine/background_layer.py
antelope_background/engine/emission.py
antelope_background/engine/flat_background.py
antelope_background/engine/live_background.py
antelope_background/engine/product_flow.py
antelope_background/engine/tarjan_stack.py
antelope_background/providers/__init__.py
antelope_background/providers/bm_dynamic.py
antelope_background/providers/bm_static.py
antelope_background/providers/check_terms.py
antelope_background-0.3.3.dist-info/licenses/LICENSE
antelope_background-0.3.3.dist-info/METADATA
antelope_background-0.3.3.dist-info/WHEEL
antelope_background-0.3.3.dist-info/top_level.txt
antelope_background-0.3.3.dist-info/RECORD
