Metadata-Version: 2.4
Name: antelope_background
Version: 0.3.3
Home-page: https://github.com/AntelopeLCA/background
Author: Brandon Kuczenski
Author-email: bkuczenski@ucsb.edu
License: BSD 3-clause
License-File: LICENSE
Requires-Dist: antelope_core>=0.3.6
Requires-Dist: scipy>=1.5
Requires-Dist: numpy>=1.19
Dynamic: author
Dynamic: author-email
Dynamic: description
Dynamic: description-content-type
Dynamic: home-page
Dynamic: license
Dynamic: license-file
Dynamic: requires-dist
